nerdo/__init__.py
nerdo/main.py
nerdo-0.0.1.dist-info/LICENSE
nerdo-0.0.1.dist-info/METADATA
nerdo-0.0.1.dist-info/WHEEL
nerdo-0.0.1.dist-info/entry_points.txt
nerdo-0.0.1.dist-info/top_level.txt
nerdo-0.0.1.dist-info/RECORD
