Metadata-Version: 2.1
Name: nerdo
Version: 0.0.1
Summary: NEwly Registered DOmains
Home-page: https://github.com/hacklego/nerdo
Author: Iago Salgado
Author-email: igsalgado@protonmail.com
License: UNKNOWN
Platform: UNKNOWN
Classifier: Programming Language :: Python :: 3
Classifier: License :: OSI Approved :: GNU General Public License v3 (GPLv3)
Requires-Dist: requests
Requires-Dist: numpy
